[
  {
    "id": "7",
    "title": "The Story of More: How We Got to Climate Change and Where to Go from Here",
    "author": "Hope Jahren"
  },
  {
    "id": "6",
    "title": "No Hard Feelings: The Secret Power of Embracing Emotions at Work",
    "author": "Liz Fosslien, Mollie West Duffy"
  },
  {
    "id": "5",
    "title": "Growing Artificial Societies: Social Science From the Bottom Up",
    "author": "Joshua M. Epstein, Robert Axtell"
  },
  {
    "id": "4",
    "title": "Resilient Management",
    "author": "Lara Hogan"
  },
  {
    "id": "3",
    "title": "Invisible Women: Data Bias in a World designed for Men",
    "author": "Caroline Criado-Pérez"
  },
  {
    "id": "2",
    "title": "Notes on a Nervous Planet",
    "author": "Matt Haig"
  },
  {
    "id": "1",
    "title": "Atomic Habits: An Easy & Proven Way to Build Good Habits & Break Bad Ones",
    "author": "James Clear"
  }
]
